pyrcmip/__init__.py
pyrcmip/_version.py
pyrcmip/assessed_ranges.py
pyrcmip/cli.py
pyrcmip/database.py
pyrcmip/errors.py
pyrcmip/io.py
pyrcmip/plotting.py
pyrcmip/stats.py
pyrcmip/utils.py
pyrcmip/data/rcmip-data-submission-template-v4-0-0.xlsx
pyrcmip/data/rcmip-data-submission-template-v5-0-0.xlsx
pyrcmip/data/rcmip-data-submission-template-v5-1-0.xlsx
pyrcmip/data/rcmip3-data-submission-template-v1-0-0.xlsx
pyrcmip/metric_calculations/__init__.py
pyrcmip/metric_calculations/airborne_fraction.py
pyrcmip/metric_calculations/base.py
pyrcmip/metric_calculations/tcr.py
pyrcmip/metric_calculations/tcre.py
pyrcmip/metric_calculations/utils.py
pyrcmip/validate/__init__.py
pyrcmip/validate/utils.py
pyrcmip-2.0.0.dist-info/licenses/LICENSE
pyrcmip-2.0.0.dist-info/METADATA
pyrcmip-2.0.0.dist-info/WHEEL
pyrcmip-2.0.0.dist-info/entry_points.txt
pyrcmip-2.0.0.dist-info/top_level.txt
pyrcmip-2.0.0.dist-info/RECORD
